pylpp_boards_pp/_pylpp_boards_pp.cpython-310-darwin.so
pylpp_boards_pp/__init__.py
pylpp_boards_pp-0.4.1.dist-info/RECORD
pylpp_boards_pp-0.4.1.dist-info/WHEEL
pylpp_boards_pp-0.4.1.dist-info/COPYING
pylpp_boards_pp-0.4.1.dist-info/METADATA
