Metadata-Version: 2.1
Name: pylpp_boards_pp
Version: 0.4.1
Summary: A modern C++ driver for LPP acquisition boards
Author-Email: Alexis Jeandet <alexis.jeandet@member.fsf.org>
License: MIT License
Classifier: Development Status :: 5 - Production/Stable
Classifier: Intended Audience :: Developers
Classifier: License :: OSI Approved :: MIT License
Classifier: Natural Language :: English
Classifier: Programming Language :: Python :: 3
Classifier: Programming Language :: Python :: 3.9
Classifier: Programming Language :: Python :: 3.10
Classifier: Programming Language :: Python :: 3.11
Classifier: Programming Language :: Python :: 3.12
Classifier: Programming Language :: Python :: 3.13
Project-URL: homepage, https://github.com/jeandet/lpp_boards_pp
Project-URL: repository, https://github.com/jeandet/lpp_boards_pp
Requires-Python: >=3.9
Requires-Dist: numpy
Requires-Dist: pyyaml
